modestga/__init__.py
modestga/con_minimize.py
modestga/ga.py
modestga/individual.py
modestga/operators.py
modestga/optres.py
modestga/population.py
modestga/benchmark/__init__.py
modestga/benchmark/benchmark_1_plot.py
modestga/benchmark/benchmark_1_run.py
modestga/benchmark/benchmark_2_plot.py
modestga/benchmark/benchmark_2_run.py
modestga/benchmark/gridrun.py
modestga/benchmark/setup_reader.py
modestga/benchmark/functions/__init__.py
modestga/benchmark/functions/mishra_bird.py
modestga/benchmark/functions/rastrigin.py
modestga/benchmark/functions/rosenbrock.py
modestga/benchmark/methods/__init__.py
modestga/benchmark/methods/differential_evolution.py
modestga/benchmark/methods/monte_carlo.py
modestga/examples/__init__.py
modestga/examples/con_min_mishra_fun.py
modestga/examples/con_min_rastrigin_fun.py
modestga/examples/con_min_rosenbrock_fun.py
modestga/examples/min_noisy_fun.py
modestga/examples/min_rastrigin_fun.py
modestga/examples/min_smooth_fun.py
modestga/parallel/__init__.py
modestga/parallel/full.py
modestga/parallel/simple.py
modestga-0.6.3.dist-info/LICENSE
modestga-0.6.3.dist-info/METADATA
modestga-0.6.3.dist-info/WHEEL
modestga-0.6.3.dist-info/top_level.txt
modestga-0.6.3.dist-info/RECORD
